{
  "running_experiments": {
    "on_fe": {
      "to_do_parameters_list_path": "/ABSOLUTE/FE/PATH/params/csnn_params.txt"
    },
    "on_machine": {
      "execute_command": "./run_experiment",
      "full_path_to_executable": "/ABSOLUTE/MACHINE/PATH/csnn"
    },
    "number_of_experiments_to_run_in_parallel_on_machine": 5,
    "experiments_collection": {
      "collection_strategy": "csnn_collection.sh",
      "path_to_save_experiment_results_on_fe": "/ABSOLUTE/FE/PATH/results/csnn",
      "path_to_saved_experiment_results_on_machine": "/ABSOLUTE/MACHINE/PATH/results/csnn"
    }
  },
  "machine_setup": {
    "image_to_use": "csnn_image.yaml",
    "env_variables_list": [
      { "OMP_NUM_THREADS": "1" },
      { "CUDA_VISIBLE_DEVICES": "0" }
    ],
    "is_machine_instantiator_manual": true,
    "list_of_needed_libraries": "/ABSOLUTE/MACHINE/PATH/bootstrap/requirements.txt",
    "os_distribution_type": 1
  }
}
